audiness/__init__.py
audiness/commands/__init__.py
audiness/commands/folders.py
audiness/commands/policies.py
audiness/commands/scans.py
audiness/commands/server.py
audiness/commands/software.py
audiness/helpers.py
audiness/main.py
audiness-0.5.0.dist-info/LICENSE
audiness-0.5.0.dist-info/METADATA
audiness-0.5.0.dist-info/WHEEL
audiness-0.5.0.dist-info/entry_points.txt
audiness-0.5.0.dist-info/RECORD
