Metadata-Version: 2.1
Name: audiness
Version: 0.5.0
Summary: CLI tool to interact with Tenable's Nessus
Home-page: https://github.com/audiusGmbH/audiness
License: MIT
Keywords: vulnerabilites,nessus
Author: Fabian Affolter
Author-email: fabian-affolter@audius.de
Requires-Python: >=3.9,<4.0
Classifier: License :: OSI Approved :: MIT License
Classifier: Programming Language :: Python :: 3
Classifier: Programming Language :: Python :: 3.9
Classifier: Programming Language :: Python :: 3.10
Classifier: Programming Language :: Python :: 3.11
Classifier: Programming Language :: Python :: 3.12
Requires-Dist: pytenable (>=1.4,<2.0)
Requires-Dist: typer[all] (>=0.9,<0.10)
Requires-Dist: validators (>=0.24,<0.25)
Project-URL: Repository, https://github.com/audiusGmbH/audiness
